benchmarkplaces
