Metadata-Version: 1.0
Name: benchmark-places
Version: 0.0.8
Summary: Place abstraction
Home-page: https://github.com/usebenchmark/benchmarkplaces.git
Author: Ken Koontz
Author-email: kenneth.koontz@gmail.com
License: MIT licence, see LICENCE.txt
Platform: UNKNOWN
